acl_anthology/__init__.py
acl_anthology/anthology.py
acl_anthology/collections/__init__.py
acl_anthology/collections/bibkeys.py
acl_anthology/collections/collection.py
acl_anthology/collections/event.py
acl_anthology/collections/eventindex.py
acl_anthology/collections/index.py
acl_anthology/collections/paper.py
acl_anthology/collections/types.py
acl_anthology/collections/volume.py
acl_anthology/config.py
acl_anthology/constants.py
acl_anthology/containers.py
acl_anthology/data/schema.rnc
acl_anthology/data/unimathsymbols.txt
acl_anthology/exceptions.py
acl_anthology/files.py
acl_anthology/people/__init__.py
acl_anthology/people/index.py
acl_anthology/people/name.py
acl_anthology/people/person.py
acl_anthology/py.typed
acl_anthology/sigs.py
acl_anthology/text/__init__.py
acl_anthology/text/markuptext.py
acl_anthology/text/stopwords.py
acl_anthology/text/texmath.py
acl_anthology/utils/__init__.py
acl_anthology/utils/attrs.py
acl_anthology/utils/citation.py
acl_anthology/utils/git.py
acl_anthology/utils/ids.py
acl_anthology/utils/latex.py
acl_anthology/utils/logging.py
acl_anthology/utils/text.py
acl_anthology/utils/xml.py
acl_anthology/venues.py
acl_anthology-1.0.0.dist-info/LICENSE
acl_anthology-1.0.0.dist-info/LICENSE.header
acl_anthology-1.0.0.dist-info/METADATA
acl_anthology-1.0.0.dist-info/WHEEL
acl_anthology-1.0.0.dist-info/RECORD
