Metadata-Version: 2.3
Name: acl-anthology
Version: 1.0.0
Summary: A library for accessing the ACL Anthology
License: Apache-2.0
Author: Marcel Bollmann
Author-email: marcel@bollmann.me
Requires-Python: >=3.10, !=3.11.0, <3.15
Classifier: Development Status :: 4 - Beta
Classifier: Intended Audience :: Developers
Classifier: Intended Audience :: Science/Research
Classifier: Operating System :: MacOS :: MacOS X
Classifier: Operating System :: Microsoft :: Windows
Classifier: Operating System :: POSIX
Classifier: Topic :: Scientific/Engineering
Classifier: Topic :: Scientific/Engineering :: Interface Engine/Protocol Translator
Classifier: Topic :: Software Development :: Libraries :: Python Modules
Classifier: Programming Language :: Python :: 3.10
Classifier: Programming Language :: Python :: 3.11
Classifier: Programming Language :: Python :: 3.12
Classifier: Programming Language :: Python :: 3.13
Classifier: Programming Language :: Python :: 3.14
Requires-Dist: PyYAML (>=6.0,<7.0)
Requires-Dist: app-paths (>=0.0.7,<0.1.0)
Requires-Dist: attrs (>=24.1,<25.0)
Requires-Dist: citeproc-py (>=0.6.0,<0.7.0)
Requires-Dist: diskcache (>=5.6.1)
Requires-Dist: docopt (>=0.6.2)
Requires-Dist: gitpython (>=3.1.37)
Requires-Dist: langcodes[data] (>=3.5.0)
Requires-Dist: lxml (>=6.0.2,<7.0.0)
Requires-Dist: numpy (>=1.26.0)
Requires-Dist: omegaconf (>=2.3.0,<2.4.0)
Requires-Dist: platformdirs (>=3.11.0,<3.12.0)
Requires-Dist: pylatexenc (>=2.10,<3.0)
Requires-Dist: python-slugify[unidecode] (>=8.0.1,<8.1.0)
Requires-Dist: rich (>=13.3.5)
Requires-Dist: rnc2rng (>=2.6.6)
Requires-Dist: scipy (>=1.6.0)
Requires-Dist: stop-words (==2018.7.23)
Requires-Dist: texsoup (>=0.3.1,<0.4.0)
Requires-Dist: typing-extensions (>=4.6.0) ; python_version < "3.11"
